adelaytime.py
doublecrossing.py
doublecrossingdemo.py
drown.py
drownade.py
drowndemo.py
linerproblem.py
onecrossingdemo.py
light1-1.0.5.dist-info/METADATA
light1-1.0.5.dist-info/WHEEL
light1-1.0.5.dist-info/top_level.txt
light1-1.0.5.dist-info/RECORD
