Metadata-Version: 2.1
Name: light1
Version: 1.0.5
Summary: traffic_light_teaching
Home-page: http://www.baidu.com
Author: xiaohan
Author-email: xiahazh@163.com
License: UNKNOWN
Platform: UNKNOWN
